ripple/__init__.py
ripple/image_embedder.py
ripple/image_search.py
ripple/image_tagger.py
ripple/text_search.py
ripple/utils.py
ripple_net-0.1.5.dist-info/METADATA
ripple_net-0.1.5.dist-info/WHEEL
ripple_net-0.1.5.dist-info/licenses/LICENSE
ripple_net-0.1.5.dist-info/RECORD
