Metadata-Version: 2.3
Name: ripple_net
Version: 0.1.5
Summary: Text-image search and image tagging library
Project-URL: Homepage, https://pypi.org/project/ripple_net/
Project-URL: Repository, https://github.com/kelechi-c/ripple_net
Author-email: Chibuzo Kelechi <kelechichibuzo7@gmail.com>
License: Apache License
License-File: LICENSE
Keywords: image datasets,image search,machine learning,multimodal AI,vector embeddings
Classifier: Development Status :: 4 - Beta
Classifier: Intended Audience :: Developers
Classifier: License :: OSI Approved :: Apache Software License
Classifier: Programming Language :: Python :: 3
Classifier: Topic :: Scientific/Engineering :: Artificial Intelligence
Requires-Python: >=3.9
Requires-Dist: datasets
Requires-Dist: faiss-cpu
Requires-Dist: faiss-gpu
Requires-Dist: matplotlib
Requires-Dist: numpy
Requires-Dist: sentence-transformers
Requires-Dist: transformers
Provides-Extra: examples
Provides-Extra: test
Requires-Dist: pytest; extra == 'test'
